Metadata-Version: 1.0
Name: crammer-distributions
Version: 0.1
Summary: Gaussian and Binomial distributions
Home-page: UNKNOWN
Author: Mujeeb Lawal
Author-email: reachmujeebhere@gmail.com
License: UNKNOWN
Platform: UNKNOWN
